GDK/KaurG.py
GDK/__init__.py
KaurG/KaurG.py
KaurG/__init__.py
KaurG-0.0.1.dist-info/METADATA
KaurG-0.0.1.dist-info/WHEEL
KaurG-0.0.1.dist-info/top_level.txt
KaurG-0.0.1.dist-info/RECORD
